html_to_editorjs/__init__.py
html_to_editorjs/blocks.py
html_to_editorjs/helpers.py
html_to_editorjs/parse.py
html_to_editorjs-0.0.1.dist-info/LICENSE
html_to_editorjs-0.0.1.dist-info/METADATA
html_to_editorjs-0.0.1.dist-info/WHEEL
html_to_editorjs-0.0.1.dist-info/top_level.txt
html_to_editorjs-0.0.1.dist-info/RECORD
