Metadata-Version: 2.1
Name: html-to-editorjs
Version: 0.0.1
Summary: Convert HTML to Editor.js JSON format.
Home-page: https://github.com/vastray/html_to_editorjs
Author: Kirill Glushkov
Author-email: vastray@icloud.com
License: MIT
License-File: LICENSE
Requires-Dist: beautifulsoup4 (<4.12,>4.7)
